xontrib/bashisms.py
xontrib_bashisms-0.0.5.dist-info/LICENSE
xontrib_bashisms-0.0.5.dist-info/METADATA
xontrib_bashisms-0.0.5.dist-info/WHEEL
xontrib_bashisms-0.0.5.dist-info/top_level.txt
xontrib_bashisms-0.0.5.dist-info/RECORD
