Metadata-Version: 2.1
Name: xontrib-bashisms
Version: 0.0.5
Summary: Bash-like interactive mode extensions for the xonsh shell.
Author-email: xontrib-bashisms <no@no.no>
License: MIT License
Project-URL: Homepage, https://github.com/xonsh/xontrib-bashisms
Project-URL: Documentation, https://github.com/xonsh/xontrib-bashisms/blob/master/README.md
Project-URL: Code, https://github.com/xonsh/xontrib-bashisms
Project-URL: Issue tracker, https://github.com/xonsh/xontrib-bashisms/issues
Platform: any
Classifier: Programming Language :: Python :: 3
Classifier: License :: OSI Approved :: MIT License
Classifier: Operating System :: OS Independent
Classifier: Topic :: System :: Shells
Classifier: Topic :: System :: System Shells
Classifier: Topic :: Terminals
Requires-Python: >=3.8
License-File: LICENSE
Requires-Dist: xonsh (>=0.12.5)
Provides-Extra: dev
Requires-Dist: pytest (>=7.0) ; extra == 'dev'
